kheritageapi/__init__.py
kheritageapi/heritage.py
kheritageapi/models.py
kheritageapi/palace.py
kheritageapi/utils.py
kheritage-1.0.1.dist-info/LICENSE
kheritage-1.0.1.dist-info/METADATA
kheritage-1.0.1.dist-info/WHEEL
kheritage-1.0.1.dist-info/top_level.txt
kheritage-1.0.1.dist-info/RECORD
