Metadata-Version: 2.1
Name: kheritage
Version: 1.0.1
Summary: A Python package aimed easy abstraction of the Cultural Heritage API provided by the Cultural Heritage Administration of Korea.
Author-email: Jay Suh <jay@joseon.space>
Project-URL: Homepage, https://github.com/SuhJae/KHeritageAPI
Project-URL: Bug Tracker, https://github.com/SuhJae/KHeritageAPI/issues
Project-URL: Source Code, https://github.com/SuhJae/KHeritageAPI
Classifier: Programming Language :: Python :: 3
Classifier: License :: OSI Approved :: MIT License
Classifier: Operating System :: OS Independent
Requires-Python: >=3.7
License-File: LICENSE
